dbsl/__init__.py
dbsl/client.py
dbsl/lib/__init__.py
dbsl/lib/util/__init__.py
dbsl/lib/util/exceptions.py
dbsl/lib/util/objects.py
DBSL.py-0.0.6.dist-info/LICENSE
DBSL.py-0.0.6.dist-info/METADATA
DBSL.py-0.0.6.dist-info/WHEEL
DBSL.py-0.0.6.dist-info/top_level.txt
DBSL.py-0.0.6.dist-info/RECORD
