Metadata-Version: 2.1
Name: DBSL.py
Version: 0.0.6
Summary: API wrapper for DBSL
Home-page: https://github.com/wezacon/DBSL.py
Author: Team Wezacon
Author-email: wezacon.com@gmail.com
License: MIT
Download-URL: https://github.com/wezacon/DBSL.py/tarball/master
Keywords: DBSL,DBSL-py,wezacon,official
Platform: UNKNOWN
Requires-Dist: setuptools
Requires-Dist: requests
Requires-Dist: six
Requires-Dist: ujson
